poisson_binomial/__init__.py
poisson_binomial-0.0.1.dist-info/LICENSE
poisson_binomial-0.0.1.dist-info/METADATA
poisson_binomial-0.0.1.dist-info/WHEEL
poisson_binomial-0.0.1.dist-info/top_level.txt
poisson_binomial-0.0.1.dist-info/RECORD
