Metadata-Version: 2.1
Name: poisson-binomial
Version: 0.0.1
Summary: methods associated with poisson binomial distribution
Home-page: https://github.com/pypa/sampleproject
Author: Sarah Wooller
Author-email: s.k.wooller@sussex.ac.uk
License: UNKNOWN
Platform: UNKNOWN
Classifier: Programming Language :: Python :: 3
Classifier: License :: OSI Approved :: MIT License
Classifier: Operating System :: OS Independent
Requires-Python: >=3.0
